tests/__init__.py
tests/test_visually.py
visual/__init__.py
visual/basevisualizer.py
visual/columntypedetector.py
visual/matplotlibvisualizer.py
visual/plotlyvisualizer.py
visual/seabornvisualizer.py
visual/visually.py
visually-1.0.1.dist-info/LICENSE.txt
visually-1.0.1.dist-info/METADATA
visually-1.0.1.dist-info/WHEEL
visually-1.0.1.dist-info/top_level.txt
visually-1.0.1.dist-info/RECORD
