Metadata-Version: 2.1
Name: visually
Version: 1.0.1
Summary: A unified interface for data visualization using Matplotlib, Seaborn, and Plotly.
Home-page: https://github.com/Sariya-Ansari/visually.git
Author: Sariya Ansari
Classifier: Programming Language :: Python :: 3
Classifier: License :: OSI Approved :: MIT License
Classifier: Operating System :: OS Independent
Requires-Python: >=3.6
License-File: LICENSE.txt
Requires-Dist: pandas
Requires-Dist: matplotlib
Requires-Dist: seaborn
Requires-Dist: plotly
Requires-Dist: kaleido
